<?xml version="1.0" encoding="utf-8" ?>
<dwsync>
<file name="bootstrap-theme.css" server="ec2-3-101-106-184.us-west-1.compute.amazonaws.com//var/www/html/" local="133545726103881204" remote="133545747300000000" Dst="2" />
<file name="bootstrap-theme.css.map" server="ec2-3-101-106-184.us-west-1.compute.amazonaws.com//var/www/html/" local="133545726104266344" remote="133545747300000000" Dst="2" />
<file name="bootstrap-theme.min.css" server="ec2-3-101-106-184.us-west-1.compute.amazonaws.com//var/www/html/" local="133545726104600606" remote="133545747300000000" Dst="2" />
<file name="bootstrap-theme.min.css.map" server="ec2-3-101-106-184.us-west-1.compute.amazonaws.com//var/www/html/" local="133545726104725722" remote="133545747300000000" Dst="2" />
<file name="bootstrap.css" server="ec2-3-101-106-184.us-west-1.compute.amazonaws.com//var/www/html/" local="133545726104835395" remote="133545747300000000" Dst="2" />
<file name="bootstrap.css.map" server="ec2-3-101-106-184.us-west-1.compute.amazonaws.com//var/www/html/" local="133545726105046366" remote="133545747330000000" Dst="2" />
<file name="bootstrap.min.css" server="ec2-3-101-106-184.us-west-1.compute.amazonaws.com//var/www/html/" local="133545726105254100" remote="133545747330000000" Dst="2" />
<file name="bootstrap.min.css.map" server="ec2-3-101-106-184.us-west-1.compute.amazonaws.com//var/www/html/" local="133545726105424682" remote="133545747330000000" Dst="2" />
<file name="font-awesome.min.css" server="ec2-3-101-106-184.us-west-1.compute.amazonaws.com//var/www/html/" local="133545726105560326" remote="133545747340000000" Dst="2" />
<file name="main.css" server="ec2-3-101-106-184.us-west-1.compute.amazonaws.com//var/www/html/" local="133545726105610135" remote="133545747340000000" Dst="2" />
<file name="owl.carousel.css" server="ec2-3-101-106-184.us-west-1.compute.amazonaws.com//var/www/html/" local="133545726105669368" remote="133545747340000000" Dst="2" />
<file name="owl.theme.default.min.css" server="ec2-3-101-106-184.us-west-1.compute.amazonaws.com//var/www/html/" local="133545726105743117" remote="133545747340000000" Dst="2" />
<file name="templatemo-style.css" server="ec2-3-101-106-184.us-west-1.compute.amazonaws.com//var/www/html/" local="133545726105838266" remote="133545747340000000" Dst="2" />
</dwsync>